{
  "AbyssJewel": {
    "crusader_tag": null,
    "elder_tag": null,
    "hunter_tag": null,
    "name": "Abyss Jewel",
    "redeemer_tag": null,
    "shaper_tag": null,
    "warlord_tag": null
  },
  "Active Skill Gem": {
    "crusader_tag": null,
    "elder_tag": null,
    "hunter_tag": null,
    "name": "Active Skill Gems",
    "redeemer_tag": null,
    "shaper_tag": null,
    "warlord_tag": null
  },
  "Amulet": {
    "crusader_tag": "amulet_crusader",
    "elder_tag": "amulet_elder",
    "hunter_tag": "amulet_basilisk",
    "name": "Amulets",
    "redeemer_tag": "amulet_eyrie",
    "shaper_tag": "amulet_shaper",
    "warlord_tag": "amulet_adjudicator"
  },
  "AtlasRegionUpgradeItem": {
    "crusader_tag": null,
    "elder_tag": null,
    "hunter_tag": null,
    "name": "Atlas Region Upgrade Item",
    "redeemer_tag": null,
    "shaper_tag": null,
    "warlord_tag": null
  },
  "Belt": {
    "crusader_tag": "belt_crusader",
    "elder_tag": "belt_elder",
    "hunter_tag": "belt_basilisk",
    "name": "Belts",
    "redeemer_tag": "belt_eyrie",
    "shaper_tag": "belt_shaper",
    "warlord_tag": "belt_adjudicator"
  },
  "Body Armour": {
    "crusader_tag": "body_armour_crusader",
    "elder_tag": "body_armour_elder",
    "hunter_tag": "body_armour_basilisk",
    "name": "Body Armours",
    "redeemer_tag": "body_armour_eyrie",
    "shaper_tag": "body_armour_shaper",
    "warlord_tag": "body_armour_adjudicator"
  },
  "Boots": {
    "crusader_tag": "boots_crusader",
    "elder_tag": "boots_elder",
    "hunter_tag": "boots_basilisk",
    "name": "Boots",
    "redeemer_tag": "boots_eyrie",
    "shaper_tag": "boots_shaper",
    "warlord_tag": "boots_adjudicator"
  },
  "Bow": {
    "crusader_tag": "bow_crusader",
    "elder_tag": "bow_elder",
    "hunter_tag": "bow_basilisk",
    "name": "Bows",
    "redeemer_tag": "bow_eyrie",
    "shaper_tag": "bow_shaper",
    "warlord_tag": "bow_adjudicator"
  },
  "Claw": {
    "crusader_tag": "claw_crusader",
    "elder_tag": "claw_elder",
    "hunter_tag": "claw_basilisk",
    "name": "Claws",
    "redeemer_tag": "claw_eyrie",
    "shaper_tag": "claw_shaper",
    "warlord_tag": "claw_adjudicator"
  },
  "Currency": {
    "crusader_tag": null,
    "elder_tag": null,
    "hunter_tag": null,
    "name": "Currency",
    "redeemer_tag": null,
    "shaper_tag": null,
    "warlord_tag": null
  },
  "Dagger": {
    "crusader_tag": "dagger_crusader",
    "elder_tag": "dagger_elder",
    "hunter_tag": "dagger_basilisk",
    "name": "Daggers",
    "redeemer_tag": "dagger_eyrie",
    "shaper_tag": "dagger_shaper",
    "warlord_tag": "dagger_adjudicator"
  },
  "DelveSocketableCurrency": {
    "crusader_tag": null,
    "elder_tag": null,
    "hunter_tag": null,
    "name": "Delve Socketable Currency",
    "redeemer_tag": null,
    "shaper_tag": null,
    "warlord_tag": null
  },
  "DelveStackableSocketableCurrency": {
    "crusader_tag": null,
    "elder_tag": null,
    "hunter_tag": null,
    "name": "Delve Stackable Socketable Currency",
    "redeemer_tag": null,
    "shaper_tag": null,
    "warlord_tag": null
  },
  "DivinationCard": {
    "crusader_tag": null,
    "elder_tag": null,
    "hunter_tag": null,
    "name": "Divination Card",
    "redeemer_tag": null,
    "shaper_tag": null,
    "warlord_tag": null
  },
  "FishingRod": {
    "crusader_tag": null,
    "elder_tag": null,
    "hunter_tag": null,
    "name": "Fishing Rods",
    "redeemer_tag": null,
    "shaper_tag": null,
    "warlord_tag": null
  },
  "Gloves": {
    "crusader_tag": "gloves_crusader",
    "elder_tag": "gloves_elder",
    "hunter_tag": "gloves_basilisk",
    "name": "Gloves",
    "redeemer_tag": "gloves_eyrie",
    "shaper_tag": "gloves_shaper",
    "warlord_tag": "gloves_adjudicator"
  },
  "HeistBlueprint": {
    "crusader_tag": null,
    "elder_tag": null,
    "hunter_tag": null,
    "name": "Blueprint",
    "redeemer_tag": null,
    "shaper_tag": null,
    "warlord_tag": null
  },
  "HeistContract": {
    "crusader_tag": null,
    "elder_tag": null,
    "hunter_tag": null,
    "name": "Contract",
    "redeemer_tag": null,
    "shaper_tag": null,
    "warlord_tag": null
  },
  "HeistEquipmentReward": {
    "crusader_tag": null,
    "elder_tag": null,
    "hunter_tag": null,
    "name": "Heist Brooch",
    "redeemer_tag": null,
    "shaper_tag": null,
    "warlord_tag": null
  },
  "HeistEquipmentTool": {
    "crusader_tag": null,
    "elder_tag": null,
    "hunter_tag": null,
    "name": "Heist Tool",
    "redeemer_tag": null,
    "shaper_tag": null,
    "warlord_tag": null
  },
  "HeistEquipmentUtility": {
    "crusader_tag": null,
    "elder_tag": null,
    "hunter_tag": null,
    "name": "Heist Cloak",
    "redeemer_tag": null,
    "shaper_tag": null,
    "warlord_tag": null
  },
  "HeistEquipmentWeapon": {
    "crusader_tag": null,
    "elder_tag": null,
    "hunter_tag": null,
    "name": "Heist Gear",
    "redeemer_tag": null,
    "shaper_tag": null,
    "warlord_tag": null
  },
  "HeistObjective": {
    "crusader_tag": null,
    "elder_tag": null,
    "hunter_tag": null,
    "name": "Heist Target",
    "redeemer_tag": null,
    "shaper_tag": null,
    "warlord_tag": null
  },
  "Helmet": {
    "crusader_tag": "helmet_crusader",
    "elder_tag": "helmet_elder",
    "hunter_tag": "helmet_basilisk",
    "name": "Helmets",
    "redeemer_tag": "helmet_eyrie",
    "shaper_tag": "helmet_shaper",
    "warlord_tag": "helmet_adjudicator"
  },
  "HiddenItem": {
    "crusader_tag": null,
    "elder_tag": null,
    "hunter_tag": null,
    "name": "Hidden Item",
    "redeemer_tag": null,
    "shaper_tag": null,
    "warlord_tag": null
  },
  "HideoutDoodad": {
    "crusader_tag": null,
    "elder_tag": null,
    "hunter_tag": null,
    "name": "Hideout Doodads",
    "redeemer_tag": null,
    "shaper_tag": null,
    "warlord_tag": null
  },
  "HybridFlask": {
    "crusader_tag": null,
    "elder_tag": null,
    "hunter_tag": null,
    "name": "Hybrid Flasks",
    "redeemer_tag": null,
    "shaper_tag": null,
    "warlord_tag": null
  },
  "Incubator": {
    "crusader_tag": null,
    "elder_tag": null,
    "hunter_tag": null,
    "name": "Incubator",
    "redeemer_tag": null,
    "shaper_tag": null,
    "warlord_tag": null
  },
  "IncursionItem": {
    "crusader_tag": null,
    "elder_tag": null,
    "hunter_tag": null,
    "name": "Incursion Item",
    "redeemer_tag": null,
    "shaper_tag": null,
    "warlord_tag": null
  },
  "Jewel": {
    "crusader_tag": null,
    "elder_tag": null,
    "hunter_tag": null,
    "name": "Jewel",
    "redeemer_tag": null,
    "shaper_tag": null,
    "warlord_tag": null
  },
  "LabyrinthItem": {
    "crusader_tag": null,
    "elder_tag": null,
    "hunter_tag": null,
    "name": "Labyrinth Item",
    "redeemer_tag": null,
    "shaper_tag": null,
    "warlord_tag": null
  },
  "LabyrinthMapItem": {
    "crusader_tag": null,
    "elder_tag": null,
    "hunter_tag": null,
    "name": "Labyrinth Map Item",
    "redeemer_tag": null,
    "shaper_tag": null,
    "warlord_tag": null
  },
  "LabyrinthTrinket": {
    "crusader_tag": null,
    "elder_tag": null,
    "hunter_tag": null,
    "name": "Labyrinth Trinket",
    "redeemer_tag": null,
    "shaper_tag": null,
    "warlord_tag": null
  },
  "LargeRelic": {
    "crusader_tag": null,
    "elder_tag": null,
    "hunter_tag": null,
    "name": "Large Relics",
    "redeemer_tag": null,
    "shaper_tag": null,
    "warlord_tag": null
  },
  "Leaguestone": {
    "crusader_tag": null,
    "elder_tag": null,
    "hunter_tag": null,
    "name": "Leaguestones",
    "redeemer_tag": null,
    "shaper_tag": null,
    "warlord_tag": null
  },
  "LifeFlask": {
    "crusader_tag": null,
    "elder_tag": null,
    "hunter_tag": null,
    "name": "Life Flasks",
    "redeemer_tag": null,
    "shaper_tag": null,
    "warlord_tag": null
  },
  "ManaFlask": {
    "crusader_tag": null,
    "elder_tag": null,
    "hunter_tag": null,
    "name": "Mana Flasks",
    "redeemer_tag": null,
    "shaper_tag": null,
    "warlord_tag": null
  },
  "Map": {
    "crusader_tag": null,
    "elder_tag": null,
    "hunter_tag": null,
    "name": "Maps",
    "redeemer_tag": null,
    "shaper_tag": null,
    "warlord_tag": null
  },
  "MapFragment": {
    "crusader_tag": null,
    "elder_tag": null,
    "hunter_tag": null,
    "name": "Map Fragments",
    "redeemer_tag": null,
    "shaper_tag": null,
    "warlord_tag": null
  },
  "MediumRelic": {
    "crusader_tag": null,
    "elder_tag": null,
    "hunter_tag": null,
    "name": "Medium Relics",
    "redeemer_tag": null,
    "shaper_tag": null,
    "warlord_tag": null
  },
  "MetamorphosisDNA": {
    "crusader_tag": null,
    "elder_tag": null,
    "hunter_tag": null,
    "name": "Metamorph Sample",
    "redeemer_tag": null,
    "shaper_tag": null,
    "warlord_tag": null
  },
  "Microtransaction": {
    "crusader_tag": null,
    "elder_tag": null,
    "hunter_tag": null,
    "name": "Microtransactions",
    "redeemer_tag": null,
    "shaper_tag": null,
    "warlord_tag": null
  },
  "MiscMapItem": {
    "crusader_tag": null,
    "elder_tag": null,
    "hunter_tag": null,
    "name": "Misc Map Items",
    "redeemer_tag": null,
    "shaper_tag": null,
    "warlord_tag": null
  },
  "One Hand Axe": {
    "crusader_tag": "axe_crusader",
    "elder_tag": "axe_elder",
    "hunter_tag": "axe_basilisk",
    "name": "One Hand Axes",
    "redeemer_tag": "axe_eyrie",
    "shaper_tag": "axe_shaper",
    "warlord_tag": "axe_adjudicator"
  },
  "One Hand Mace": {
    "crusader_tag": "mace_crusader",
    "elder_tag": "mace_elder",
    "hunter_tag": "mace_basilisk",
    "name": "One Hand Maces",
    "redeemer_tag": "mace_eyrie",
    "shaper_tag": "mace_shaper",
    "warlord_tag": "mace_adjudicator"
  },
  "One Hand Sword": {
    "crusader_tag": "sword_crusader",
    "elder_tag": "sword_elder",
    "hunter_tag": "sword_basilisk",
    "name": "One Hand Swords",
    "redeemer_tag": "sword_eyrie",
    "shaper_tag": "sword_shaper",
    "warlord_tag": "sword_adjudicator"
  },
  "PantheonSoul": {
    "crusader_tag": null,
    "elder_tag": null,
    "hunter_tag": null,
    "name": "Pantheon Soul",
    "redeemer_tag": null,
    "shaper_tag": null,
    "warlord_tag": null
  },
  "QuestItem": {
    "crusader_tag": null,
    "elder_tag": null,
    "hunter_tag": null,
    "name": "Quest Items",
    "redeemer_tag": null,
    "shaper_tag": null,
    "warlord_tag": null
  },
  "Quiver": {
    "crusader_tag": "quiver_crusader",
    "elder_tag": "quiver_elder",
    "hunter_tag": "quiver_basilisk",
    "name": "Quivers",
    "redeemer_tag": "quiver_eyrie",
    "shaper_tag": "quiver_shaper",
    "warlord_tag": "quiver_adjudicator"
  },
  "Ring": {
    "crusader_tag": "ring_crusader",
    "elder_tag": "ring_elder",
    "hunter_tag": "ring_basilisk",
    "name": "Rings",
    "redeemer_tag": "ring_eyrie",
    "shaper_tag": "ring_shaper",
    "warlord_tag": "ring_adjudicator"
  },
  "Rune Dagger": {
    "crusader_tag": "rune_dagger_crusader",
    "elder_tag": "rune_dagger_elder",
    "hunter_tag": "rune_dagger_basilisk",
    "name": "Rune Daggers",
    "redeemer_tag": "rune_dagger_eyrie",
    "shaper_tag": "rune_dagger_shaper",
    "warlord_tag": "rune_dagger_adjudicator"
  },
  "Sceptre": {
    "crusader_tag": "sceptre_crusader",
    "elder_tag": "sceptre_elder",
    "hunter_tag": "sceptre_basilisk",
    "name": "Sceptres",
    "redeemer_tag": "sceptre_eyrie",
    "shaper_tag": "sceptre_shaper",
    "warlord_tag": "sceptre_adjudicator"
  },
  "Shield": {
    "crusader_tag": "shield_crusader",
    "elder_tag": "shield_elder",
    "hunter_tag": "shield_basilisk",
    "name": "Shields",
    "redeemer_tag": "shield_eyrie",
    "shaper_tag": "shield_shaper",
    "warlord_tag": "shield_adjudicator"
  },
  "SmallRelic": {
    "crusader_tag": null,
    "elder_tag": null,
    "hunter_tag": null,
    "name": "Small Relics",
    "redeemer_tag": null,
    "shaper_tag": null,
    "warlord_tag": null
  },
  "StackableCurrency": {
    "crusader_tag": null,
    "elder_tag": null,
    "hunter_tag": null,
    "name": "Stackable Currency",
    "redeemer_tag": null,
    "shaper_tag": null,
    "warlord_tag": null
  },
  "Staff": {
    "crusader_tag": "staff_crusader",
    "elder_tag": "staff_elder",
    "hunter_tag": "staff_basilisk",
    "name": "Staves",
    "redeemer_tag": "staff_eyrie",
    "shaper_tag": "staff_shaper",
    "warlord_tag": "staff_adjudicator"
  },
  "Support Skill Gem": {
    "crusader_tag": null,
    "elder_tag": null,
    "hunter_tag": null,
    "name": "Support Skill Gems",
    "redeemer_tag": null,
    "shaper_tag": null,
    "warlord_tag": null
  },
  "Thrusting One Hand Sword": {
    "crusader_tag": "sword_crusader",
    "elder_tag": "sword_elder",
    "hunter_tag": "sword_basilisk",
    "name": "Thrusting One Hand Swords",
    "redeemer_tag": "sword_eyrie",
    "shaper_tag": "sword_shaper",
    "warlord_tag": "sword_adjudicator"
  },
  "Trinket": {
    "crusader_tag": null,
    "elder_tag": null,
    "hunter_tag": null,
    "name": "Trinkets",
    "redeemer_tag": null,
    "shaper_tag": null,
    "warlord_tag": null
  },
  "Two Hand Axe": {
    "crusader_tag": "2h_axe_crusader",
    "elder_tag": "2h_axe_elder",
    "hunter_tag": "2h_axe_basilisk",
    "name": "Two Hand Axes",
    "redeemer_tag": "2h_axe_eyrie",
    "shaper_tag": "2h_axe_shaper",
    "warlord_tag": "2h_axe_adjudicator"
  },
  "Two Hand Mace": {
    "crusader_tag": "2h_mace_crusader",
    "elder_tag": "2h_mace_elder",
    "hunter_tag": "2h_mace_basilisk",
    "name": "Two Hand Maces",
    "redeemer_tag": "2h_mace_eyrie",
    "shaper_tag": "2h_mace_shaper",
    "warlord_tag": "2h_mace_adjudicator"
  },
  "Two Hand Sword": {
    "crusader_tag": "2h_sword_crusader",
    "elder_tag": "2h_sword_elder",
    "hunter_tag": "2h_sword_basilisk",
    "name": "Two Hand Swords",
    "redeemer_tag": "2h_sword_eyrie",
    "shaper_tag": "2h_sword_shaper",
    "warlord_tag": "2h_sword_adjudicator"
  },
  "UNUSED2": {
    "crusader_tag": null,
    "elder_tag": null,
    "hunter_tag": null,
    "name": "",
    "redeemer_tag": null,
    "shaper_tag": null,
    "warlord_tag": null
  },
  "UNUSED3": {
    "crusader_tag": null,
    "elder_tag": null,
    "hunter_tag": null,
    "name": "",
    "redeemer_tag": null,
    "shaper_tag": null,
    "warlord_tag": null
  },
  "UNUSED4": {
    "crusader_tag": null,
    "elder_tag": null,
    "hunter_tag": null,
    "name": "",
    "redeemer_tag": null,
    "shaper_tag": null,
    "warlord_tag": null
  },
  "Unarmed": {
    "crusader_tag": null,
    "elder_tag": null,
    "hunter_tag": null,
    "name": "",
    "redeemer_tag": null,
    "shaper_tag": null,
    "warlord_tag": null
  },
  "UniqueFragment": {
    "crusader_tag": null,
    "elder_tag": null,
    "hunter_tag": null,
    "name": "Piece",
    "redeemer_tag": null,
    "shaper_tag": null,
    "warlord_tag": null
  },
  "UniqueShard": {
    "crusader_tag": null,
    "elder_tag": null,
    "hunter_tag": null,
    "name": "Shard",
    "redeemer_tag": null,
    "shaper_tag": null,
    "warlord_tag": null
  },
  "UniqueShardBase": {
    "crusader_tag": null,
    "elder_tag": null,
    "hunter_tag": null,
    "name": "Shard Heart",
    "redeemer_tag": null,
    "shaper_tag": null,
    "warlord_tag": null
  },
  "UtilityFlask": {
    "crusader_tag": null,
    "elder_tag": null,
    "hunter_tag": null,
    "name": "Utility Flasks",
    "redeemer_tag": null,
    "shaper_tag": null,
    "warlord_tag": null
  },
  "UtilityFlaskCritical": {
    "crusader_tag": null,
    "elder_tag": null,
    "hunter_tag": null,
    "name": "Critical Utility Flasks",
    "redeemer_tag": null,
    "shaper_tag": null,
    "warlord_tag": null
  },
  "Wand": {
    "crusader_tag": "wand_crusader",
    "elder_tag": "wand_elder",
    "hunter_tag": "wand_basilisk",
    "name": "Wands",
    "redeemer_tag": "wand_eyrie",
    "shaper_tag": "wand_shaper",
    "warlord_tag": "wand_adjudicator"
  },
  "Warstaff": {
    "crusader_tag": "warstaff_crusader",
    "elder_tag": "warstaff_elder",
    "hunter_tag": "warstaff_basilisk",
    "name": "Warstaves",
    "redeemer_tag": "warstaff_eyrie",
    "shaper_tag": "warstaff_shaper",
    "warlord_tag": "warstaff_adjudicator"
  }
}